cloudnetpy_qc/__init__.py
cloudnetpy_qc/coverage.py
cloudnetpy_qc/py.typed
cloudnetpy_qc/quality.py
cloudnetpy_qc/utils.py
cloudnetpy_qc/variables.py
cloudnetpy_qc/version.py
cloudnetpy_qc/data/area-type-table.xml
cloudnetpy_qc/data/cf-standard-name-table.xml
cloudnetpy_qc/data/data_quality_config.ini
cloudnetpy_qc/data/standardized-region-list.xml
cloudnetpy_qc-1.30.3.dist-info/licenses/LICENSE
cloudnetpy_qc-1.30.3.dist-info/METADATA
cloudnetpy_qc-1.30.3.dist-info/WHEEL
cloudnetpy_qc-1.30.3.dist-info/top_level.txt
cloudnetpy_qc-1.30.3.dist-info/RECORD
