Metadata-Version: 2.4
Name: cloudnetpy_qc
Version: 1.30.3
Summary: Quality control routines for CloudnetPy products
Author-email: Finnish Meteorological Institute <actris-cloudnet@fmi.fi>
License: MIT License
Project-URL: Homepage, https://github.com/actris-cloudnet/cloudnetpy-qc
Project-URL: Repository, https://github.com/actris-cloudnet/cloudnetpy-qc
Project-URL: Changelog, https://github.com/actris-cloudnet/cloudnetpy-qc/blob/main/CHANGELOG.md
Classifier: Development Status :: 5 - Production/Stable
Classifier: Intended Audience :: Science/Research
Classifier: License :: OSI Approved :: MIT License
Classifier: Operating System :: OS Independent
Classifier: Programming Language :: Python :: 3
Classifier: Topic :: Scientific/Engineering :: Atmospheric Science
Requires-Python: >=3.10
License-File: LICENSE
Requires-Dist: cfchecker
Requires-Dist: netCDF4
Requires-Dist: numpy
Requires-Dist: requests
Requires-Dist: scipy
Provides-Extra: test
Requires-Dist: mypy; extra == "test"
Requires-Dist: pytest-flakefinder; extra == "test"
Requires-Dist: types-requests; extra == "test"
Provides-Extra: dev
Requires-Dist: pre-commit; extra == "dev"
Requires-Dist: release-version; extra == "dev"
Dynamic: license-file
